pfb/__init__.py
pfb/base.py
pfb/cli.py
pfb/commands/__init__.py
pfb/commands/add.py
pfb/commands/etl.py
pfb/commands/import.py
pfb/commands/rename.py
pfb/commands/show.py
pfb/etl/__init__.py
pfb/etl/etl.py
pfb/exporters/__init__.py
pfb/exporters/gremlin.py
pfb/exporters/tsv.py
pfb/importers/__init__.py
pfb/importers/gen3dict.py
pfb/importers/json.py
pfb/importers/tsv.py
pfb/reader.py
pfb/writer.py
pypfb-0.6.2.dist-info/METADATA
pypfb-0.6.2.dist-info/WHEEL
pypfb-0.6.2.dist-info/entry_points.txt
pypfb-0.6.2.dist-info/licenses/LICENSE
pypfb-0.6.2.dist-info/licenses/NOTICE
pypfb-0.6.2.dist-info/RECORD
