Metadata-Version: 2.4
Name: pypfb
Version: 0.6.2
Summary: Python SDK for PFB format
License: Apache-2.0
License-File: LICENSE
License-File: NOTICE
Author: CTDS UChicago
Author-email: cdis@uchicago.edu
Requires-Python: >=3.9,<4
Classifier: License :: OSI Approved :: Apache Software License
Classifier: Programming Language :: Python :: 3
Classifier: Programming Language :: Python :: 3.9
Classifier: Programming Language :: Python :: 3.10
Classifier: Programming Language :: Python :: 3.11
Classifier: Programming Language :: Python :: 3.12
Classifier: Programming Language :: Python :: 3.13
Classifier: Programming Language :: Python :: 3.14
Requires-Dist: PyYAML (>=6.0.1)
Requires-Dist: aiohttp (>=3.6.3)
Requires-Dist: click (>=8.1.7)
Requires-Dist: dictionaryutils (>=3.4.8)
Requires-Dist: fastavro (>=1.11.0)
Requires-Dist: gen3 (>=4.11.3)
Requires-Dist: gen3dictionary (>=2.0.3)
Requires-Dist: importlib_metadata (>=3.6.0) ; python_full_version <= "3.9.0"
Requires-Dist: python-json-logger (>=2.0.0)
